[
{"word":"Danse Classique","forbidden":["Ballet","Pointes","Tutus","Grâce","Scène"],"theme":"arts","difficulty":"easy"},
{"word":"Danse Contemporaine","forbidden":["Moderne","Corps","Expression","Spectacle","Mouvement"],"theme":"arts","difficulty":"medium"},
{"word":"Hip-Hop","forbidden":["Breakdance","Urbain","Musique","Style","Jeunes"],"theme":"arts","difficulty":"easy"},
{"word":"Salsa","forbidden":["Latino","Musique","Couple","Cuba","Rythme"],"theme":"arts","difficulty":"easy"},
{"word":"Tango","forbidden":["Argentine","Couple","Passion","Accordéon","Danse"],"theme":"arts","difficulty":"medium"},
{"word":"Flamenco","forbidden":["Espagne","Castagnettes","Robe","Passion","Talon"],"theme":"arts","difficulty":"medium"},
{"word":"Valse","forbidden":["Viennoise","Couple","Tourner","Bal","Élégant"],"theme":"arts","difficulty":"easy"},
{"word":"Rumba","forbidden":["Cuba","Latino","Couple","Lent","Sensuel"],"theme":"arts","difficulty":"medium"},
{"word":"Cha-cha","forbidden":["Cuba","Latino","Rythme","Rapide","Trois Pas"],"theme":"arts","difficulty":"medium"},
{"word":"Jive","forbidden":["Rock","Américain","Rapide","Swing","Couple"],"theme":"arts","difficulty":"medium"},
{"word":"Quickstep","forbidden":["Rapide","Couple","Salle","Standard","Anglais"],"theme":"arts","difficulty":"hard"},
{"word":"Foxtrot","forbidden":["Standard","Couple","Américain","Lent","Salle"],"theme":"arts","difficulty":"hard"},
{"word":"Samba","forbidden":["Brésil","Carnaval","Rythme","Brésilien","Fête"],"theme":"arts","difficulty":"medium"},
{"word":"Paso Doble","forbidden":["Espagne","Corrida","Toréador","Standard","Compétition"],"theme":"arts","difficulty":"hard"},
{"word":"Swing","forbidden":["Jazz","Américain","Années","Couple","Vitesse"],"theme":"arts","difficulty":"medium"},
{"word":"Lindy Hop","forbidden":["Swing","Américain","Harlem","Jazz","Aérien"],"theme":"arts","difficulty":"hard"},
{"word":"Boogie Woogie","forbidden":["Rock","Américain","Rapide","Années","Swing"],"theme":"arts","difficulty":"hard"},
{"word":"Danse Africaine","forbidden":["Afrique","Tribale","Rythme","Corps","Tradition"],"theme":"arts","difficulty":"medium"},
{"word":"Bharatanatyam","forbidden":["Indien","Classique","Mudra","Tradition","Yeux"],"theme":"arts","difficulty":"hard"},
{"word":"Kathak","forbidden":["Indien","Classique","Pieds","Tourner","Cloches"],"theme":"arts","difficulty":"hard"},
{"word":"Capoeira","forbidden":["Brésil","Combat","Danse","Musique","Afro"],"theme":"arts","difficulty":"medium"},
{"word":"Zumba","forbidden":["Fitness","Latino","Groupe","Musique","Exercice"],"theme":"arts","difficulty":"easy"},
{"word":"Kizomba","forbidden":["Angola","Couple","Lent","Sensuel","Lusophone"],"theme":"arts","difficulty":"hard"},
{"word":"Zouk","forbidden":["Antilles","Couple","Brésil","Romantique","Lent"],"theme":"arts","difficulty":"medium"},
{"word":"Mouvements Breakdance","forbidden":["Sol","Acrobatique","Tête","Tourner","Hip-Hop"],"theme":"arts","difficulty":"medium"},
{"word":"Chorégraphie","forbidden":["Danse","Créer","Mouvements","Scène","Metteur"],"theme":"arts","difficulty":"medium"},
{"word":"Chorégraphe","forbidden":["Créer","Danses","Artiste","Scène","Mouvements"],"theme":"arts","difficulty":"medium"},
{"word":"Danseur Étoile","forbidden":["Ballet","Premier","Opéra","Classique","Titre"],"theme":"arts","difficulty":"hard"},
{"word":"Corps de Ballet","forbidden":["Groupe","Danseurs","Ballet","Ensemble","Classique"],"theme":"arts","difficulty":"hard"},
{"word":"Opéra","forbidden":["Chanter","Lyrique","Scène","Orchestre","Costume"],"theme":"arts","difficulty":"medium"},
{"word":"Opéra Comique","forbidden":["Parlé","Chanté","France","Léger","Mixte"],"theme":"arts","difficulty":"hard"},
{"word":"Opérette","forbidden":["Légère","Chanter","Jouer","Comique","Populaire"],"theme":"arts","difficulty":"hard"},
{"word":"Comédie Musicale","forbidden":["Chanter","Danser","Broadway","Spectacle","Américain"],"theme":"arts","difficulty":"easy"},
{"word":"Revue","forbidden":["Spectacle","Cabaret","Numéros","Plumes","Paris"],"theme":"arts","difficulty":"medium"},
{"word":"Cabaret","forbidden":["Spectacle","Scène","Bar","Artistes","Numéros"],"theme":"arts","difficulty":"medium"},
{"word":"Cirque","forbidden":["Acrobate","Clown","Chapiteau","Jongler","Animaux"],"theme":"arts","difficulty":"easy"},
{"word":"Mime","forbidden":["Silencieux","Corps","Marcel Marceau","Exprimer","Geste"],"theme":"arts","difficulty":"medium"},
{"word":"Marionnettiste","forbidden":["Marionnettes","Fils","Guignol","Manipuler","Spectacle"],"theme":"arts","difficulty":"medium"},
{"word":"Ventriloque","forbidden":["Poupée","Parler","Bouche","Fermée","Illusion"],"theme":"arts","difficulty":"medium"},
{"word":"Prestidigitateur","forbidden":["Magie","Tours","Mains","Escamoter","Illusionniste"],"theme":"arts","difficulty":"hard"},
{"word":"Illusionniste","forbidden":["Magie","Disparaître","Spectacle","Truc","Public"],"theme":"arts","difficulty":"medium"},
{"word":"Cracheur de Feu","forbidden":["Feu","Cracher","Jongler","Spectacle","Cirque"],"theme":"arts","difficulty":"medium"},
{"word":"Jongleur","forbidden":["Balles","Lancer","Rattraper","Cirque","Trois"],"theme":"arts","difficulty":"easy"},
{"word":"Acrobate","forbidden":["Souplesse","Équilibre","Cirque","Sauter","Corps"],"theme":"arts","difficulty":"easy"},
{"word":"Trapéziste","forbidden":["Cirque","Haut","Trapèze","Voltiger","Filet"],"theme":"arts","difficulty":"medium"},
{"word":"Funambule","forbidden":["Corde","Équilibre","Haut","Cirque","Marcher"],"theme":"arts","difficulty":"medium"},
{"word":"Clown","forbidden":["Nez","Rouge","Cirque","Faire","Rire"],"theme":"arts","difficulty":"easy"},
{"word":"Arlequin","forbidden":["Losange","Costume","Commedia","Personnage","Coloré"],"theme":"arts","difficulty":"hard"},
{"word":"Polichinelle","forbidden":["Guignol","Bosse","Personnage","Secret","Punch"],"theme":"arts","difficulty":"hard"},
{"word":"Pierrot","forbidden":["Blanc","Triste","Lune","Personnage","Collerette"],"theme":"arts","difficulty":"hard"},
{"word":"Commedia dell'Arte","forbidden":["Italie","Masques","Improviser","Personnages","Renaissance"],"theme":"arts","difficulty":"hard"},
{"word":"Théâtre de Rue","forbidden":["Dehors","Public","Gratuit","Spectacle","Artiste"],"theme":"arts","difficulty":"medium"},
{"word":"Spectacle Son et Lumière","forbidden":["Monument","Nuit","Musique","Raconter","Histoire"],"theme":"arts","difficulty":"medium"},
{"word":"Feux d'Artifice","forbidden":["Nuit","Couleurs","Ciel","Bruit","Fête"],"theme":"arts","difficulty":"easy"},
{"word":"Théâtre d'Ombres","forbidden":["Mains","Lumière","Silhouette","Mur","Chine"],"theme":"arts","difficulty":"medium"},
{"word":"Kamishibaï","forbidden":["Japonais","Images","Raconter","Carton","Portable"],"theme":"arts","difficulty":"hard"},
{"word":"Conte Vivant","forbidden":["Raconter","Oral","Histoire","Geste","Public"],"theme":"arts","difficulty":"medium"},
{"word":"One-Man-Show","forbidden":["Seul","Scène","Humour","Spectacle","Raconter"],"theme":"arts","difficulty":"medium"},
{"word":"Stand-Up","forbidden":["Comique","Micro","Debout","Parler","Public"],"theme":"arts","difficulty":"medium"},
{"word":"Improvisation","forbidden":["Sans","Préparer","Théâtre","Spontané","Groupe"],"theme":"arts","difficulty":"medium"},
{"word":"Concours de Plaidoirie","forbidden":["Avocat","Défendre","Argumentation","Compétition","Parler"],"theme":"arts","difficulty":"hard"},
{"word":"Battle de Rap","forbidden":["Versus","Improviser","Rimes","Scène","Gagner"],"theme":"arts","difficulty":"medium"},
{"word":"Spoken Word","forbidden":["Poésie","Micro","Performer","Public","Texte"],"theme":"arts","difficulty":"hard"},
{"word":"Beatbox","forbidden":["Bouche","Sons","Rythme","Hip-Hop","Imiter"],"theme":"arts","difficulty":"medium"},
{"word":"A Cappella","forbidden":["Chanter","Sans","Accompagnement","Voix","Groupe"],"theme":"arts","difficulty":"medium"},
{"word":"Chorale","forbidden":["Chanter","Groupe","Ensemble","Voix","Partition"],"theme":"arts","difficulty":"easy"}
]
